{
	"id": "9fb11147-843f-4a13-bee3-3de45c2821d2",
	"name": "Batch16",
	"values": [
		{
			"key": "id",
			"value": 5068,
			"type": "any",
			"enabled": true
		},
		{
			"key": "token",
			"value": "1f4d49366b232ef",
			"type": "any",
			"enabled": true
		},
		{
			"key": "baseUrl",
			"value": "https://restful-booker.herokuapp.com",
			"type": "default",
			"enabled": true
		},
		{
			"key": "checkin",
			"value": "2023-10-20",
			"type": "any",
			"enabled": true
		},
		{
			"key": "checkout",
			"value": "2024-02-24",
			"type": "any",
			"enabled": true
		},
		{
			"key": "lastName",
			"value": "Littel",
			"type": "any",
			"enabled": true
		},
		{
			"key": "firstName",
			"value": "Saul",
			"type": "any",
			"enabled": true
		}
	],
	"_postman_variable_scope": "environment",
	"_postman_exported_at": "2023-06-19T20:18:43.987Z",
	"_postman_exported_using": "Postman/10.14.9"
}